bng_dis_probability/Binomialdistribution.py
bng_dis_probability/Gaussiandistribution.py
bng_dis_probability/Generaldistribution.py
bng_dis_probability/__init__.py
bng_dis_probability-0.2.dist-info/METADATA
bng_dis_probability-0.2.dist-info/WHEEL
bng_dis_probability-0.2.dist-info/top_level.txt
bng_dis_probability-0.2.dist-info/RECORD
