Metadata-Version: 2.1
Name: bng-dis-probability
Version: 0.2
Summary: Gaussian and Binomial distributions
Home-page: UNKNOWN
Author: Mohammed Hamza Malik
Author-email: m.h.m.i.malik@gmail.com
License: UNKNOWN
Platform: UNKNOWN
